pylons_sphinx_latesturl/__init__.py
pylons_sphinx_latesturl-0.2.dist-info/DESCRIPTION.rst
pylons_sphinx_latesturl-0.2.dist-info/METADATA
pylons_sphinx_latesturl-0.2.dist-info/RECORD
pylons_sphinx_latesturl-0.2.dist-info/WHEEL
pylons_sphinx_latesturl-0.2.dist-info/metadata.json
pylons_sphinx_latesturl-0.2.dist-info/top_level.txt
