Metadata-Version: 2.0
Name: pylons-sphinx-latesturl
Version: 0.2
Summary: Sphinx extension: generate "latest" URL for versioned docs
Home-page: https://github.com/Pylons/pylons_sphinx_latesturl
Author: Agendaless Consulting
Author-email: repoze-dev@lists.repoze.org
License: BSD-derived (https://github.com/Pylons/pylons_sphinx_latesturl/LICENSE.txt)
Keywords: web documentation
Platform: UNKNOWN
Classifier: Development Status :: 3 - Alpha
Classifier: Intended Audience :: Developers
Classifier: Programming Language :: Python
Classifier: Programming Language :: Python :: 2.6
Classifier: Programming Language :: Python :: 2.7
Classifier: Programming Language :: Python :: 3
Classifier: Programming Language :: Python :: 3.2
Classifier: Programming Language :: Python :: 3.3
Classifier: Programming Language :: Python :: Implementation :: CPython
Classifier: Programming Language :: Python :: Implementation :: PyPy
Requires-Dist: Sphinx (>=1.0)
Requires-Dist: setuptools
